{
  "main": {
    "id": "19a25a951838786f",
    "type": "split",
    "children": [
      {
        "id": "ad283d7cd2910368",
        "type": "tabs",
        "children": [
          {
            "id": "91708e7b42f222ab",
            "type": "leaf",
            "pinned": true,
            "state": {
              "type": "markdown",
              "state": {
                "file": "docs/MOC.md",
                "mode": "source",
                "backlinks": false,
                "source": false
              },
              "pinned": true
            }
          },
          {
            "id": "cc9fad7d64ae2b4e",
            "type": "leaf",
            "state": {
              "type": "markdown",
              "state": {
                "file": "docs/22-6-std-string-appending.md",
                "mode": "source",
                "backlinks": false,
                "source": false
              }
            }
          }
        ],
        "currentTab": 1
      }
    ],
    "direction": "vertical"
  },
  "left": {
    "id": "37740572e4927497",
    "type": "split",
    "children": [
      {
        "id": "a254ad40c4b196a5",
        "type": "tabs",
        "children": [
          {
            "id": "b9cdb44997e9824e",
            "type": "leaf",
            "state": {
              "type": "file-explorer",
              "state": {
                "sortOrder": "alphabetical"
              }
            }
          },
          {
            "id": "54f64ac35b54f74b",
            "type": "leaf",
            "state": {
              "type": "search",
              "state": {
                "query": "",
                "matchingCase": false,
                "explainSearch": false,
                "collapseAll": false,
                "extraContext": false,
                "sortOrder": "alphabetical"
              }
            }
          },
          {
            "id": "4047f47d9adb4df3",
            "type": "leaf",
            "state": {
              "type": "starred",
              "state": {}
            }
          },
          {
            "id": "757996903fd3a515",
            "type": "leaf",
            "state": {
              "type": "recent-files",
              "state": {}
            }
          }
        ]
      }
    ],
    "direction": "horizontal",
    "width": 254,
    "collapsed": true
  },
  "right": {
    "id": "2d4c7ea0a4baec3c",
    "type": "split",
    "children": [
      {
        "id": "8fc510f6b8f500ff",
        "type": "tabs",
        "children": [
          {
            "id": "443be626e233958a",
            "type": "leaf",
            "state": {
              "type": "outline",
              "state": {
                "file": "docs/22-6-std-string-appending.md"
              }
            }
          },
          {
            "id": "007fc127cd13d94a",
            "type": "leaf",
            "state": {
              "type": "tag",
              "state": {
                "sortOrder": "alphabetical",
                "useHierarchy": false
              }
            }
          },
          {
            "id": "43fe58f8d0453352",
            "type": "leaf",
            "state": {
              "type": "backlink",
              "state": {
                "file": "docs/22-6-std-string-appending.md",
                "collapseAll": true,
                "extraContext": false,
                "sortOrder": "alphabetical",
                "showSearch": true,
                "searchQuery": "",
                "backlinkCollapsed": false,
                "unlinkedCollapsed": true
              }
            }
          }
        ],
        "currentTab": 2
      }
    ],
    "direction": "horizontal",
    "width": 300,
    "collapsed": true
  },
  "active": "cc9fad7d64ae2b4e",
  "lastOpenFiles": [
    "docs/MOC.md",
    "docs/22-5-std-string-assignment-and-swapping.md",
    "docs/22-4-std-string-character-access-and-conversion-to-C-style-arrays.md",
    "docs/22-1-std-string-and-std-wstring.md",
    "docs/22-3-std-string-length-and-capacity.md",
    "docs/22-2-std-string-construction-and-destruction.md",
    "docs/23-7-random-file-IO.md",
    "docs/23-6-basic-file-IO.md",
    "docs/destructors.md",
    "docs/13-x-Chapter-13-comprehensive-quiz.md"
  ]
}